roop_elasticsearch/__init__.py
roop_elasticsearch/elasticsearch.py
roop_elasticsearch-0.0.3.dist-info/METADATA
roop_elasticsearch-0.0.3.dist-info/WHEEL
roop_elasticsearch-0.0.3.dist-info/top_level.txt
roop_elasticsearch-0.0.3.dist-info/RECORD
