Metadata-Version: 2.1
Name: roop_elasticsearch
Version: 0.0.3
Summary: Generic package which can be used for elasticsearch
Author: Roopendra
Author-email: roopendra.naik@informa.com
Classifier: Programming Language :: Python :: 3
Classifier: License :: OSI Approved :: MIT License
Classifier: Operating System :: OS Independent
Requires-Python: >=3.6
Requires-Dist: elasticsearch
